mirror_lambda_environment/__init__.py
mirror_lambda_environment/decorator.py
mirror_lambda_environment/utils.py
mirror_lambda_environment-1.0.0.dist-info/LICENSE
mirror_lambda_environment-1.0.0.dist-info/METADATA
mirror_lambda_environment-1.0.0.dist-info/WHEEL
mirror_lambda_environment-1.0.0.dist-info/top_level.txt
mirror_lambda_environment-1.0.0.dist-info/RECORD
