Metadata-Version: 2.2
Name: mirror-lambda-environment
Version: 1.0.0
Summary: A handy dev tool to mirror a Lambda's environment variables locally.
Author: Tayler Kemsley
License: MIT License
Classifier: License :: OSI Approved :: MIT License
Classifier: Programming Language :: Python
Classifier: Programming Language :: Python :: 3
Requires-Python: >=3.9
License-File: LICENSE
Requires-Dist: boto3==1.36.4
Requires-Dist: inject-environment-variables>=1.1.0
Requires-Dist: simple-term-menu==1.6.6
Provides-Extra: dev
Requires-Dist: tox; extra == "dev"
Requires-Dist: pytest; extra == "dev"
Requires-Dist: mypy; extra == "dev"
Requires-Dist: flake8; extra == "dev"
